ws2webhook/__init__.py
ws2webhook/cli.py
ws2webhook/const.py
ws2webhook/main.py
ws2webhook/version.py
ws2webhook-0.1.10.dist-info/LICENSE
ws2webhook-0.1.10.dist-info/METADATA
ws2webhook-0.1.10.dist-info/WHEEL
ws2webhook-0.1.10.dist-info/entry_points.txt
ws2webhook-0.1.10.dist-info/RECORD
